tests/core/__init__.py
tests/core/test_block_manager.py
tests/core/test_chunked_prefill_scheduler.py
tests/core/test_scheduler.py
tests/core/utils.py
tests/core/block/__init__.py
tests/core/block/conftest.py
tests/core/block/test_block_manager_v2.py
tests/core/block/test_block_table.py
tests/core/block/test_common.py
tests/core/block/test_cpu_gpu_block_allocator.py
tests/core/block/test_naive_block.py
tests/core/block/test_prefix_caching_block.py
tests/lora/__init__.py
tests/lora/conftest.py
tests/lora/test_baichuan.py
tests/lora/test_chatglm3.py
tests/lora/test_gemma.py
tests/lora/test_layer_variation.py
tests/lora/test_layers.py
tests/lora/test_llama.py
tests/lora/test_lora.py
tests/lora/test_lora_checkpoints.py
tests/lora/test_lora_manager.py
tests/lora/test_mixtral.py
tests/lora/test_punica.py
tests/lora/test_quant_model.py
tests/lora/test_tokenizer_group.py
tests/lora/test_utils.py
tests/lora/test_worker.py
tests/lora/utils.py
tests/spec_decode/__init__.py
tests/spec_decode/test_batch_expansion.py
tests/spec_decode/test_metrics.py
tests/spec_decode/test_multi_step_worker.py
tests/spec_decode/test_ngram_worker.py
tests/spec_decode/test_spec_decode_worker.py
tests/spec_decode/test_utils.py
tests/spec_decode/utils.py
tests/spec_decode/e2e/__init__.py
tests/spec_decode/e2e/conftest.py
tests/spec_decode/e2e/test_compatibility.py
tests/spec_decode/e2e/test_multistep_correctness.py
tests/spec_decode/e2e/test_ngram_correctness.py
tests/tensorizer_loader/__init__.py
tests/tensorizer_loader/tensorize_vllm_model_for_testing.py
tests/tensorizer_loader/test_tensorizer.py
tests/tokenization/__init__.py
tests/tokenization/test_cached_tokenizer.py
tests/tokenization/test_detokenize.py
tests/tokenization/test_tokenizer.py
tests/tokenization/test_tokenizer_group.py
tests/worker/__init__.py
tests/worker/test_model_runner.py
tests/worker/test_swap.py
vllm/_C.cpython-310-x86_64-linux-gnu.so
vllm/__init__.py
vllm/_custom_ops.py
vllm/_moe_C.cpython-310-x86_64-linux-gnu.so
vllm_acc-0.4.21716571491.2888474.dist-info/LICENSE
vllm_acc-0.4.21716571491.2888474.dist-info/METADATA
vllm_acc-0.4.21716571491.2888474.dist-info/WHEEL
vllm_acc-0.4.21716571491.2888474.dist-info/top_level.txt
vllm_acc-0.4.21716571491.2888474.dist-info/RECORD
